kenmerkendewaarden/__init__.py
kenmerkendewaarden/data_analysis.py
kenmerkendewaarden/data_retrieve.py
kenmerkendewaarden/gemiddeldgetij.py
kenmerkendewaarden/havengetallen.py
kenmerkendewaarden/overschrijding.py
kenmerkendewaarden/slotgemiddelden.py
kenmerkendewaarden/tidalextremes.py
kenmerkendewaarden/tidalindicators.py
kenmerkendewaarden/tidalindicators_springneap.py
kenmerkendewaarden/utils.py
kenmerkendewaarden-0.5.0.dist-info/licenses/LICENSE
kenmerkendewaarden-0.5.0.dist-info/METADATA
kenmerkendewaarden-0.5.0.dist-info/WHEEL
kenmerkendewaarden-0.5.0.dist-info/top_level.txt
kenmerkendewaarden-0.5.0.dist-info/RECORD
