Metadata-Version: 2.4
Name: kenmerkendewaarden
Version: 0.5.0
Summary: Derive indicators from waterlevel measurements
Maintainer-email: Jelmer Veenstra <jelmer.veenstra@deltares.nl>
License-Expression: LGPL-3.0
Project-URL: Home, https://github.com/deltares-research/kenmerkendewaarden
Project-URL: Code, https://github.com/deltares-research/kenmerkendewaarden
Project-URL: Issues, https://github.com/deltares-research/kenmerkendewaarden/issues
Keywords: kenmerkendewaarden
Classifier: Development Status :: 2 - Pre-Alpha
Classifier: Intended Audience :: Science/Research
Classifier: Operating System :: OS Independent
Classifier: Topic :: Scientific/Engineering :: Information Analysis
Classifier: Programming Language :: Python
Classifier: Programming Language :: Python :: 3
Classifier: Programming Language :: Python :: 3.9
Classifier: Programming Language :: Python :: 3.10
Classifier: Programming Language :: Python :: 3.11
Classifier: Programming Language :: Python :: 3.12
Classifier: Programming Language :: Python :: 3.13
Classifier: Programming Language :: Python :: 3.14
Requires-Python: >=3.9
License-File: LICENSE
Requires-Dist: numpy>=1.25.0
Requires-Dist: pandas>=2.1.4
Requires-Dist: matplotlib>=3.7.0
Requires-Dist: netcdf4>=1.5.6
Requires-Dist: xarray>=2023.4.0
Requires-Dist: rws-ddlpy>=0.8.0
Requires-Dist: hatyan>=2.13.0
Requires-Dist: statsmodels>=0.14.5
Requires-Dist: pyproj>=3.1.0
Requires-Dist: pooch>=1.1.0
Provides-Extra: dev
Requires-Dist: bump2version>=0.5.11; extra == "dev"
Requires-Dist: flake8; extra == "dev"
Requires-Dist: pytest; extra == "dev"
Requires-Dist: pytest-cov; extra == "dev"
Requires-Dist: twine; extra == "dev"
Requires-Dist: build; extra == "dev"
Requires-Dist: black; extra == "dev"
Provides-Extra: docs
Requires-Dist: sphinx>=1.8.1; extra == "docs"
Requires-Dist: sphinx_mdinclude; extra == "docs"
Requires-Dist: pydata-sphinx-theme; extra == "docs"
Provides-Extra: examples
Requires-Dist: jupyter; extra == "examples"
Requires-Dist: notebook; extra == "examples"
Dynamic: license-file
